add_header_comment/__init__.py
add_header_comment/__main__.py
add_header_comment-1.0.1.dist-info/licenses/LICENSE
add_header_comment-1.0.1.dist-info/METADATA
add_header_comment-1.0.1.dist-info/WHEEL
add_header_comment-1.0.1.dist-info/entry_points.txt
add_header_comment-1.0.1.dist-info/top_level.txt
add_header_comment-1.0.1.dist-info/RECORD
