Metadata-Version: 2.4
Name: add-header-comment
Version: 1.0.1
Summary: Add or update the header of a file with the appropriate comment style.
Home-page: https://github.com/sayari-analytics/add-header-comment
Author: Nathaniel Young
Author-email: nyoung@sayari.com
Maintainer: Sayari Labs
Maintainer-email: 
License: MIT
Project-URL: Bug Tracker, https://github.com/sayari-analytics/add-header-comment/issues
Project-URL: Source Code, https://github.com/sayari-analytics/add-header-comment
Keywords: pre-commit,file header,license,automation
Classifier: Environment :: Console
Classifier: Intended Audience :: Developers
Classifier: License :: OSI Approved :: MIT License
Classifier: Operating System :: OS Independent
Classifier: Programming Language :: Python
Classifier: Programming Language :: Python :: 3
Classifier: Programming Language :: Python :: 3 :: Only
Requires-Python: >=3.5
License-File: LICENSE
Dynamic: author
Dynamic: author-email
Dynamic: classifier
Dynamic: description
Dynamic: description-content-type
Dynamic: home-page
Dynamic: keywords
Dynamic: license
Dynamic: license-file
Dynamic: maintainer
Dynamic: project-url
Dynamic: requires-python
Dynamic: summary
